odoo/addons/sale_validity/README.rst
odoo/addons/sale_validity/__init__.py
odoo/addons/sale_validity/__manifest__.py
odoo/addons/sale_validity/i18n/ca.po
odoo/addons/sale_validity/i18n/de.po
odoo/addons/sale_validity/i18n/el_GR.po
odoo/addons/sale_validity/i18n/es.po
odoo/addons/sale_validity/i18n/es_ES.po
odoo/addons/sale_validity/i18n/es_VE.po
odoo/addons/sale_validity/i18n/fi.po
odoo/addons/sale_validity/i18n/fr.po
odoo/addons/sale_validity/i18n/hr.po
odoo/addons/sale_validity/i18n/hr_HR.po
odoo/addons/sale_validity/i18n/hu.po
odoo/addons/sale_validity/i18n/it.po
odoo/addons/sale_validity/i18n/nl.po
odoo/addons/sale_validity/i18n/nl_NL.po
odoo/addons/sale_validity/i18n/pt.po
odoo/addons/sale_validity/i18n/pt_BR.po
odoo/addons/sale_validity/i18n/ro.po
odoo/addons/sale_validity/i18n/sale_validity.pot
odoo/addons/sale_validity/i18n/sk.po
odoo/addons/sale_validity/i18n/sl.po
odoo/addons/sale_validity/i18n/tr.po
odoo/addons/sale_validity/i18n/tr_TR.po
odoo/addons/sale_validity/i18n/vi_VN.po
odoo/addons/sale_validity/i18n/zh_CN.po
odoo/addons/sale_validity/models/__init__.py
odoo/addons/sale_validity/models/company.py
odoo/addons/sale_validity/models/res_config_settings.py
odoo/addons/sale_validity/models/sale_order.py
odoo/addons/sale_validity/readme/CONFIGURE.rst
odoo/addons/sale_validity/readme/CONTRIBUTORS.rst
odoo/addons/sale_validity/readme/DESCRIPTION.rst
odoo/addons/sale_validity/readme/USAGE.rst
odoo/addons/sale_validity/static/description/icon.png
odoo/addons/sale_validity/static/description/index.html
odoo/addons/sale_validity/tests/__init__.py
odoo/addons/sale_validity/tests/test_sale_validity.py
odoo/addons/sale_validity/views/res_config_settings.xml
odoo13_addon_sale_validity-13.0.1.0.1.dist-info/METADATA
odoo13_addon_sale_validity-13.0.1.0.1.dist-info/WHEEL
odoo13_addon_sale_validity-13.0.1.0.1.dist-info/top_level.txt
odoo13_addon_sale_validity-13.0.1.0.1.dist-info/RECORD
